Workbook

Sheet 00-读我
A1: 金山工厂物流成本预算框架（给财务四类：运费 / 外仓 / 进口手续费 / 其他）
A2: 项 | B2: 说明
A3: 用途 | B3: 正确往下做月度预算的驱动结构。产量未按月锁定前，不填假精确 RMB。
A4: 财务假设 | B4: 2026 年底现有产线或迁独山；2027 开启 Chromate & Silicone 本地生产。
A5: 产量口径（已有、待 MP 月分解） | B5: Alex 2026-08：含硅 72 T/年 + 含铬 400 T/年 = 472 T/年成品，约 39 T/月（均匀假设）。
A6: 真正卡住运费的缺口 | B6: 472 T 是成品产量，不是进口原料吨。缺：BOM、进口 vs 国产原料占比、到港卸点（洋山→金山 还是 先独山再调拨）。
A7: CIF 口径 | B7: 德→中空运/海运由德国指定、CIF。国际段运费通常在采购价里，不进中国「运费」科目。中国运费=到港后内陆+国内配送+独山↔金山调拨。须财务书面确认。
A8: 外仓口径（已定） | B8: 金山自有仓，不租外仓。本列填 0。叉车采购与仓操作人员进「其他」，不要塞进外仓。长春/沧州外仓仅汽车，C&S 成品是否走外仓待销售确认，默认不进本预算。
A9: 两套时间 | B9: 2026 Q4：现有产线迁独山=一次性搬迁物流，不是 2027 运行费率。2027：C&S 投产月度运行成本。
A10: 事实源 | B10: projects/2026-08-jinshan-wh-restart.md；knowledge/01-company、03-network、04-operations。

Sheet 01-产量与驱动
A1: 驱动 | B1: 建议值 / 公式 | C1: 状态 | D1: Owner | E1: 不填会怎样
A2: 成品年产量 含硅 T | B2: 72 | C2: 已有（Alex 2026-08） | D2: 生产 | E2: 无月计划则只能均匀摊 6 T/月
A3: 成品年产量 含铬 T | B3: 400 | C3: 已有（Alex 2026-08） | D3: 生产 | E3: 均匀摊 ~33 T/月
A4: 合计成品 T/年 | B4: =B2+B3 | C4: 由上两项 | D4: 生产
A5: 2027 月产量曲线 | B5: 待填 12 个数；暂可 =B4/12 | C5: 缺 | D5: 计划 MP | E5: 运费/手续费无法按月
A6: 原料投入系数（原料T / 成品T） | B6: 待工艺 BOM | C6: 缺 | D6: 生产/工艺 | E6: 有成品吨仍算不出原料吨
A7: 进口原料占比 % | B7: 待采购：德国进口 vs 国内采购 | C7: 缺 | D7: 采购 | E7: 进口运费与手续费无法算
A8: 进口卸点 | B8: 洋山直送金山 / 先独山再调拨（二选一） | C8: 缺 | D8: 物流+MP | E8: 内陆运费差一倍搬运
A9: CIF 国际运费是否进中国运费科目 | B9: 建议否（含在采购价） | C9: 待财务书面 | D9: 财务 | E9: 与德国重复计算或漏计
A10: 关税/增值税是否进本表 | B10: 建议否（单独税项，不进四类） | C10: 待财务书面 | D10: 财务 | E10: 四类被税撑爆，无法比物流
A11: 成品是否经长春/沧州外仓 | B11: 建议否（C&S 非汽车卫星仓默认） | C11: 待销售 | D11: 销售 | E11: 外仓列可能不该为 0
A12: 金山→客户配送模式 | B12: 公路危货零担（国内主模式） | C12: 网络已运行 | D12: 物流 | E12: 缺客户结构则吨公里未知
A13: 仓常驻人数 | B13: 2（方案 A）；或 3（方案 B 不依赖独山 Backup） | C13: 物流已建议 | D13: 物流/厂长 | E13: 其他-人力无法编
A14: 独山 Backup 人天/月 | B14: 待厂长锁定上限 | C14: 缺 | D14: 厂长 | E14: 成本中心扯皮
A15: 新前移式 1.4T | B15: 1 台新购 | C15: 物流已建议 | D15: 物流/工程 | E15: CapEx vs 折旧问财务
A16: 新平衡重 | B16: 1 台新购；吨位待工艺 | C16: 物流已建议 | D16: 生产定吨位 | E16: 错买/晚买
A17: 2015 前移 | B17: 过渡备用，不替代新车 | C17: 现役 | D17: 物流 | E17: 勿把旧车当产能
A18: 公式（有数后再填金额）：月进口原料吨 = 月成品吨 × 原料投入系数 × 进口原料占比。中国侧进口运费驱动=该吨数（到港后内陆）。手续费驱动=进口票数或票+吨（代理报价）。国内配送驱动=月成品吨×平均运距。

Sheet 02-四类科目映射
A1: 财务四类 | B1: 子项 | C1: 进本列？ | D1: CapEx/OpEx | E1: 物流建议 | F1: 缺什么才能填 RMB
A2: 运费 | B2: CIF 汉堡/FRA→洋山/PVG 国际段 | C2: 默认否 | D2: 在采购价 | E2: 德国指定承运；中国物流不订舱。财务若要集团全成本，请另开「CIF 国际」备查列，不要与中国运费混加。 | F2: 财务确认科目
A3: 运费 | B3: 洋山/PVG→金山 进口内陆（危货公路） | C3: 是 | D3: OpEx | E3: C&S 投产后的主进口运费。若先入独山再调拨，改记调拨运费。 | F3: 月进口吨 + 卸点 + 危货费率
A4: 运费 | B4: 金山→中国客户 成品配送 | C4: 是 | D4: OpEx | E4: 国内危货零担；温控如涉及 UV/水性另列。 | F4: 客户区域结构 + 月成品吨
A5: 运费 | B5: 金山↔独山 原料/半成品/包材调拨 | C5: 是（若发生） | D5: OpEx | E5: 共用独山库存或包材时必有。含铬分区后尽量少调。 | F5: 调拨规则 + 月吨
A6: 运费 | B6: 2026 现有产线迁独山（设备/剩余库存） | C6: 一次性，可单列 2026-12 | D6: 一次性 | E6: 不是 2027 运行费率。危货搬迁+特种设备。 | F6: 搬迁清单吨位/车次
A7: 运费 | B7: 紧急空运进口 | C7: 是（例外） | D7: OpEx | E7: 不编进基线；单列应急。空运亦 CIF、德国指定。 | F7: 政策：是否允许
A8: 外仓 | B8: 金山厂内仓租赁 | C8: 否=0 | D8: — | E8: 自有空间，不租。 | F8: 无
A9: 外仓 | B9: 长春/沧州 3PL | C9: 默认否=0 | D9: OpEx 若启用 | E9: 现网仅汽车。C&S 默认不进卫星仓。 | F9: 销售是否要求外仓
A10: 外仓 | B10: 港区/危库暂存超期 | C10: 其他或运费附带 | D10: OpEx 异常 | E10: 设计为零；超期再进异常。 | F10: 不编基线
A11: 进口手续费 | B11: 报关代理 / 换单 / 港杂（CIF 到港后买方段） | C11: 是 | D11: OpEx | E11: CIF 不包含中国报关与港后费用。 | F11: 票数或吨 + 代理费率
A12: 进口手续费 | B12: 危化进口申报 / 查验陪同 | C12: 是 | D12: OpEx | E12: 含铬/含硅查验概率高于普通漆，费率可高于独山常规。 | F12: 代理报价
... A22: 其他 | B22: 出单打签系统/耗材 | C22: 否（不默认进仓） | D22: OpEx 在 Shipping/计划 | E22: 仓员不顺便做。 | F22: 主责部门

Sheet 03-2027月度四类
A1: 科目 | B1: 子项 / 驱动 | C1: 2027-01 | D1: 2027-02 | E1: 2027-03 | F1: 2027-04 | G1: 2027-05 | H1: 2027-06 | I1: 2027-07 | J1: 2027-08 | K1: 2027-09 | L1: 2027-10 | M1: 2027-11 | N1: 2027-12 | O1: 2027合计 | P1: 填数规则
A2: 驱动 | B2: 成品产量 T（默认 472/12，MP 可改） | C2: ='01-产量与驱动'!$B$4/12 | D2: ='01-产量与驱动'!$B$4/12 | E2: ='01-产量与驱动'!$B$4/12 | F2: ='01-产量与驱动'!$B$4/12 | G2: ='01-产量与驱动'!$B$4/12 | H2: ='01-产量与驱动'!$B$4/12 | I2: ='01-产量与驱动'!$B$4/12 | J2: ='01-产量与驱动'!$B$4/12 | ... N2: ='01-产量与驱动'!$B$4/12 | O2: =SUM(C2:N2) | P2: 产量驱动行。MP 给爬坡后改各月，不要改合计公式。
A3: 驱动 | B3: 进口原料 T（=产量×投入系数×进口占比；缺系数则留空） | O3: =SUM(C3:N3) | P3: 有费率×驱动后再填。禁止估一个整数充数。
A4: 运费 | B4: 到港后内陆 洋山/PVG→金山 | O4: =SUM(C4:N4) | P4: 有费率×驱动后再填。禁止估一个整数充数。
A5: 运费 | B5: 金山→客户 成品配送 | O5: =SUM(C5:N5) | P5: 有费率×驱动后再填。禁止估一个整数充数。
A6: 运费 | B6: 金山↔独山 调拨 | O6: =SUM(C6:N6) | P6: 有费率×驱动后再填。禁止估一个整数充数。
A7: 运费 | B7: 紧急空运（基线 0） | C7: 0 | D7: 0 | E7: 0 | F7: 0 | G7: 0 | H7: 0 | I7: 0 | J7: 0 | K7: 0 | L7: 0 | M7: 0 | N7: 0 | O7: =SUM(C7:N7) | P7: 基线 0。启用外仓/空运时改对应月。
A8: 运费 | B8: 运费小计 | C8: =C4+C5+C6+C7 | D8: =D4+D5+D6+D7 | E8: =E4+E5+E6+E7 | F8: =F4+F5+F6+F7 | G8: =G4+G5+G6+G7 | H8: =H4+H5+H6+H7 | I8: =I4+I5+I6+I7 | J8: =J4+J5+J6+J7 | ... N8: =N4+N5+N6+N7 | O8: =SUM(C8:N8) | P8: 运费小计
A9: 外仓 | B9: 金山厂内租赁（自有=0） | C9: 0 | D9: 0 | E9: 0 | F9: 0 | G9: 0 | H9: 0 | I9: 0 | J9: 0 | K9: 0 | L9: 0 | M9: 0 | N9: 0 | O9: =SUM(C9:N9) | P9: 基线 0。启用外仓/空运时改对应月。
A10: 外仓 | B10: 长春/沧州 3PL（默认 0） | C10: 0 | D10: 0 | E10: 0 | F10: 0 | G10: 0 | H10: 0 | I10: 0 | J10: 0 | K10: 0 | L10: 0 | M10: 0 | N10: 0 | O10: =SUM(C10:N10) | P10: 基线 0。启用外仓/空运时改对应月。
A11: 外仓 | B11: 外仓小计 | C11: =C9+C10 | D11: =D9+D10 | E11: =E9+E10 | F11: =F9+F10 | G11: =G9+G10 | H11: =H9+H10 | I11: =I9+I10 | J11: =J9+J10 | ... N11: =N9+N10 | O11: =SUM(C11:N11) | P11: 外仓小计（自有仓应为 0）
A12: 进口手续费 | B12: 报关/换单/港杂 | O12: =SUM(C12:N12) | P12: 有费率×驱动后再填。禁止估一个整数充数。
A13: 进口手续费 | B13: 危化申报/查验 | O13: =SUM(C13:N13) | P13: 有费率×驱动后再填。禁止估一个整数充数。
A14: 进口手续费 | B14: 进口手续费小计 | C14: =C12+C13 | D14: =D12+D13 | E14: =E12+E13 | F14: =F12+F13 | G14: =G12+G13 | H14: =H12+H13 | I14: =I12+I13 | J14: =J12+J13 | ... N14: =N12+N13 | O14: =SUM(C14:N14) | P14: 进口手续费小计（不含关税增值税）
A15: 其他 | B15: 仓操作 2 人（月薪资，HR 填） | O15: =SUM(C15:N15) | P15: 有费率×驱动后再填。禁止估一个整数充数。
A16: 其他 | B16: 独山 Backup 人天 | O16: =SUM(C16:N16) | P16: 有费率×驱动后再填。禁止估一个整数充数。
A17: 其他 | B17: 叉车折旧或购入月现金（与财务选口径） | O17: =SUM(C17:N17) | P17: 有费率×驱动后再填。禁止估一个整数充数。
A18: 其他 | B18: 叉车维保 | O18: =SUM(C18:N18) | P18: 有费率×驱动后再填。禁止估一个整数充数。
A19: 其他 | B19: 办公+保洁 | O19: =SUM(C19:N19) | P19: 有费率×驱动后再填。禁止估一个整数充数。
A20: 其他 | B20: 含铬硅合规/PPE/培训（无报价则留空） | O20: =SUM(C20:N20) | P20: 有费率×驱动后再填。禁止估一个整数充数。
A21: 其他 | B21: 其他小计 | C21: =C15+C16+C17+C18+C19+C20 | D21: =D15+D16+D17+D18+D19+D20 | E21: =E15+E16+E17+E18+E19+E20 | F21: =F15+F16+F17+F18+F19+F20 | G21: =G15+G16+G17+G18+G19+G20 | H21: =H15+H16+H17+H18+H19+H20 | I21: =I15+I16+I17+I18+I19+I20 | J21: =J15+J16+J17+J18+J19+J20 | ... N21: =N15+N16+N17+N18+N19+N20 | O21: =SUM(C21:N21) | P21: 其他小计
A22: 合计 | B22: 四类合计 | C22: =C8+C11+C14+C21 | D22: =D8+D11+D14+D21 | E22: =E8+E11+E14+E21 | F22: =F8+F11+F14+F21 | G22: =G8+G11+G14+G21 | H22: =H8+H11+H14+H21 | I22: =I8+I11+I14+I21 | J22: =J8+J11+J14+J21 | ... N22: =N8+N11+N14+N21 | O22: =SUM(C22:N22) | P22: 四类合计
A24: 黄色格=待费率。绿色格=已定性为 0。蓝色小计勿手改。产量行已用 472/12；MP 给爬坡后只改第 2 行各月。进口原料行在 01 表系数齐备前保持空白。

Sheet 04-2026迁线一次性
A1: 项 | B1: 是否物流预算 | C1: 说明 | D1: RMB（待填） | E1: Owner
A2: 现有金山产线设备迁独山（特种/危货运输） | B2: 是-运费一次性 | C2: 财务邮件假设 2026 年底。与 2027 C&S 运行运费分开。 | E2: 物流+生产
A3: 剩余原料/成品迁独山 | B3: 是-运费一次性 | C3: 库存盘点后再估车次。 | E3: 仓+MP
A4: 金山仓清场、旧叉车报废/处置 | B4: 其他一次性 | C4: 2012 两台停用车不计入 2027 产能。 | E4: 工程/仓
A5: 独山接收增加的仓容/人力冲击 | B5: 不进金山四类，须书面提示财务 | C5: 独山 5 号甲类已约 80–85%。迁线可能挤独山，不是金山外仓费。 | E5: 厂长/财务
A6: 2027 投产前金山仓空窗期（人已到岗、货未到） | B6: 其他-人力 | C6: 招聘早于投产则 2026Q4–2027Q1 仍有工资。 | E6: HR/物流

Sheet 05-待确认清单
A1: # | B1: 问谁 | C1: 问题 | D1: 卡住哪一类 | E1: 状态
A2: 1 | B2: 计划 MP / 生产 | C2: 2027 年 1–12 月含硅、含铬成品产量（可先给爬坡再给稳定月） | D2: 运费、手续费 | E2: 未开始
A3: 2 | B3: 生产 / 工艺 | C3: 单位成品的原料投入系数；含铬/含硅分列 | D3: 运费、手续费 | E3: 未开始
A4: 3 | B4: 采购 | C4: 原料中德国进口 vs 国内采购的吨或金额占比 | D4: 运费、手续费 | E4: 未开始
A5: 4 | B5: 财务 Yiwen | C5: CIF 国际运费是否进中国「运费」？关税增值税是否进本四类？叉车按购入月现金还是折旧？ | D5: 全部口径 | E5: 未开始
A6: 5 | B6: 物流+MP | C6: 进口到港后直送金山，还是先独山再调拨？ | D6: 运费 | E6: 未开始
A7: 6 | B7: 销售 | C7: C&S 成品是否进长春/沧州外仓？主要客户区域？ | D7: 外仓、运费 | E7: 未开始
A8: 7 | B8: 厂长 | C8: 仓编制 A=2+Backup 还是 B=3？Backup 人天与成本中心？ | D8: 其他 | E8: 未开始
A9: 8 | B9: 生产 | C9: 平衡重吨位（单批投料+釜重）与投产月 | D9: 其他-叉车 | E9: 未开始
A10: 9 | B10: EHS | C10: 含铬存储分区、PPE、培训、废弃物主责与概算 | D10: 其他 | E10: 未开始
A11: 10 | B11: HR | C11: 仓员 2 人到位月、薪资包 | D11: 其他 | E11: 未开始
